love_code/__init__.py
love_code/love.py
zyc_love-1.0.1.dist-info/LICENSE
zyc_love-1.0.1.dist-info/METADATA
zyc_love-1.0.1.dist-info/WHEEL
zyc_love-1.0.1.dist-info/top_level.txt
zyc_love-1.0.1.dist-info/RECORD
